http_api_sdk-2.3.0.dist-info/DESCRIPTION.rst
http_api_sdk-2.3.0.dist-info/METADATA
http_api_sdk-2.3.0.dist-info/RECORD
http_api_sdk-2.3.0.dist-info/WHEEL
http_api_sdk-2.3.0.dist-info/metadata.json
http_api_sdk-2.3.0.dist-info/top_level.txt
httpapi/HTTPSDK.py
httpapi/__init__.py
