Metadata-Version: 1.2
Name: http-api-sdk
Version: 2.3.0
Summary: 扩展你的QQ/微信机器人用途，提供跨框架平台的PHP/Java/Python/NodeJS等编程语言SDK。https://github.com/ksust/HTTP--API
Home-page: https://github.com/ksust/HTTP--API
Author: ksust
Author-email: admin@ksust.com
Maintainer: ksust
Maintainer-email: admin@ksust.com
License: UNKNOWN
Platform: all
Classifier: Programming Language :: Python
Classifier: Programming Language :: Python :: Implementation
Classifier: Programming Language :: Python :: 2
Classifier: Programming Language :: Python :: 2.7
Classifier: Programming Language :: Python :: 3
Classifier: Programming Language :: Python :: 3.4
Classifier: Programming Language :: Python :: 3.5
Classifier: Programming Language :: Python :: 3.6
